brseclabcripto/__init__.py
brseclabcripto/cripto2.py
brseclabcripto/cripto3.py
brseclabcripto-2.1.0.dist-info/LICENSE
brseclabcripto-2.1.0.dist-info/METADATA
brseclabcripto-2.1.0.dist-info/WHEEL
brseclabcripto-2.1.0.dist-info/RECORD
